outflowpy/__init__.py
outflowpy/_version.py
outflowpy/analytic.py
outflowpy/coords.py
outflowpy/fast_tracer.cpython-313-x86_64-linux-gnu.so
outflowpy/fieldline.py
outflowpy/grid.py
outflowpy/hmi_download.py
outflowpy/input.py
outflowpy/interpolator.py
outflowpy/map.py
outflowpy/obtain_data.py
outflowpy/outflow.py
outflowpy/outflow_calc.cpython-313-x86_64-linux-gnu.so
outflowpy/output.py
outflowpy/pfss.py
outflowpy/plotting.py
outflowpy/sample_data.py
outflowpy/tracing.py
outflowpy/utils.py
outflowpy/utils_pfsspy.py
outflowpy-0.0.1.dist-info/licenses/LICENSE.txt
outflowpy-0.0.1.dist-info/METADATA
outflowpy-0.0.1.dist-info/WHEEL
outflowpy-0.0.1.dist-info/top_level.txt
outflowpy-0.0.1.dist-info/RECORD
