Metadata-Version: 2.4
Name: outflowpy
Version: 0.0.1
Summary: Outflow field modelling
Author: Oliver Rice
Author-email: Oliver Rice <oliverricesolar@gmail.com>
License: MIT
Requires-Python: >=3.9
License-File: LICENSE.txt
Requires-Dist: numpy
Requires-Dist: astropy
Requires-Dist: matplotlib
Requires-Dist: sunpy
Requires-Dist: reproject
Requires-Dist: mpl_animators
Requires-Dist: bs4
Requires-Dist: lxml
Requires-Dist: zeep
Requires-Dist: drms
Requires-Dist: scikit-image
Requires-Dist: pyvista
Dynamic: author
Dynamic: license-file
